{
  "kind": "collectionType",
  "collectionName": "options",
  "info": {
    "singularName": "option",
    "pluralName": "options",
    "displayName": "Options",
    "description": ""
  },
  "options": {
    "draftAndPublish": false
  },
  "pluginOptions": {},
  "attributes": {
    "title": {
      "type": "string",
      "required": true
    },
    "sort_order": {
      "type": "integer",
      "required": true,
      "unique": true,
      "default": 1
    },
    "option_id": {
      "type": "uid",
      "default": "0",
      "required": true
    }
  }
}
